vbai/__init__.py
vbai/cli.py
vbai/py.typed
vbai/configs/__init__.py
vbai/configs/defaults.py
vbai/data/__init__.py
vbai/data/datasets.py
vbai/data/transforms.py
vbai/models/__init__.py
vbai/models/attention.py
vbai/models/backbone.py
vbai/models/multitask.py
vbai/training/__init__.py
vbai/training/callbacks.py
vbai/training/losses.py
vbai/training/trainer.py
vbai/utils/__init__.py
vbai/utils/analysis.py
vbai/utils/visualization.py
vbai-0.1.9.dist-info/licenses/LICENSE
vbai-0.1.9.dist-info/METADATA
vbai-0.1.9.dist-info/WHEEL
vbai-0.1.9.dist-info/entry_points.txt
vbai-0.1.9.dist-info/top_level.txt
vbai-0.1.9.dist-info/RECORD
