Metadata-Version: 2.4
Name: vbai
Version: 0.1.9
Summary: Visual Brain AI - Multi-task brain MRI analysis library
Home-page: https://github.com/Neurazum-AI-Department/vbai
Author: Neurazum
Author-email: Neurazum <contact@neurazum.com>
Maintainer: Neurazum AI Department
License: MIT
Project-URL: Homepage, https://github.com/Neurazum-AI-Department/vbai
Project-URL: Documentation, https://github.com/Neurazum-AI-Department/vbai/blob/main/README.md
Project-URL: Repository, https://github.com/Neurazum-AI-Department/vbai
Project-URL: Issues, https://github.com/Neurazum-AI-Department/vbai/issues
Keywords: deep-learning,medical-imaging,brain-mri,dementia,tumor-detection,pytorch,multi-task-learning,image-processing,computer-vision,image-classification,image-segmentation,health,healthcare
Classifier: Development Status :: 3 - Alpha
Classifier: Intended Audience :: Science/Research
Classifier: Intended Audience :: Healthcare Industry
Classifier: License :: OSI Approved :: MIT License
Classifier: Operating System :: OS Independent
Classifier: Programming Language :: Python :: 3
Classifier: Programming Language :: Python :: 3.8
Classifier: Programming Language :: Python :: 3.9
Classifier: Programming Language :: Python :: 3.10
Classifier: Programming Language :: Python :: 3.11
Classifier: Programming Language :: Python :: 3.12
Classifier: Topic :: Scientific/Engineering :: Artificial Intelligence
Classifier: Topic :: Scientific/Engineering :: Medical Science Apps.
Classifier: Topic :: Scientific/Engineering :: Image Processing
Requires-Python: >=3.8
License-File: LICENSE
Requires-Dist: torch>=1.9.0
Requires-Dist: torchvision>=0.10.0
Requires-Dist: Pillow>=8.0.0
Requires-Dist: numpy>=1.19.0
Provides-Extra: full
Requires-Dist: matplotlib>=3.3.0; extra == "full"
Requires-Dist: opencv-python>=4.5.0; extra == "full"
Requires-Dist: tqdm>=4.60.0; extra == "full"
Requires-Dist: tensorboard>=2.4.0; extra == "full"
Requires-Dist: pyyaml>=5.4.0; extra == "full"
Provides-Extra: dev
Requires-Dist: pytest>=6.0.0; extra == "dev"
Requires-Dist: pytest-cov>=2.0.0; extra == "dev"
Requires-Dist: black>=21.0; extra == "dev"
Requires-Dist: isort>=5.0.0; extra == "dev"
Requires-Dist: flake8>=3.9.0; extra == "dev"
Requires-Dist: mypy>=0.900; extra == "dev"
Provides-Extra: docs
Requires-Dist: sphinx>=4.0.0; extra == "docs"
Requires-Dist: sphinx-rtd-theme>=0.5.0; extra == "docs"
Requires-Dist: sphinx-autodoc-typehints>=1.12.0; extra == "docs"
Provides-Extra: all
Requires-Dist: vbai[dev,docs,full]; extra == "all"
Dynamic: author
Dynamic: home-page
Dynamic: license-file
Dynamic: requires-python
